rag_tool_package/__init__.py
rag_tool_package/tools/__init__.py
rag_tool_package/tools/rag_tool.py
rag_tool_package/tools/utils.py
rag_tool_package/yamls/rag_tool.yaml
tests/__init__.py
tests/test_rag_tool.py
rag_tool_package-0.2.0.dist-info/METADATA
rag_tool_package-0.2.0.dist-info/WHEEL
rag_tool_package-0.2.0.dist-info/entry_points.txt
rag_tool_package-0.2.0.dist-info/top_level.txt
rag_tool_package-0.2.0.dist-info/RECORD
